pip_list/__init__.py
pip_list/cli.py
pip_list-0.1.5.dist-info/licenses/LICENSE
pip_list-0.1.5.dist-info/METADATA
pip_list-0.1.5.dist-info/WHEEL
pip_list-0.1.5.dist-info/entry_points.txt
pip_list-0.1.5.dist-info/top_level.txt
pip_list-0.1.5.dist-info/RECORD
