Metadata-Version: 2.4
Name: pip-list
Version: 0.1.5
Summary: List installed pip packages with their installed size, supports sorting and filtering.
Author-email: Mayank Kumar Poddar <mayankpdr@gmail.com>
License: MIT
Project-URL: Homepage, https://github.com/mynkpdr/pip-list
Keywords: pip,list,packages,size,cli
Classifier: Programming Language :: Python :: 3
Classifier: License :: OSI Approved :: MIT License
Classifier: Operating System :: OS Independent
Requires-Python: >=3.6
License-File: LICENSE
Dynamic: license-file
